{
  "courtois": {
    "price": 25.0,
    "currency": "EUR"
  },
  "lunin": {
    "price": 4.0,
    "currency": "EUR"
  },
  "fran-garcia": {
    "price": 0.0199,
    "currency": "ETH"
  },
  "mendy": {
    "price": 1.0,
    "currency": "EUR"
  },
  "militao": {
    "price": 4.1,
    "currency": "EUR"
  },
  "rudiger": {
    "price": 1.0,
    "currency": "EUR"
  },
  "raul-asencio": {
    "price": 2.1,
    "currency": "EUR"
  },
  "huijsen": {
    "price": 9.9,
    "currency": "EUR"
  },
  "alvaro-fernandez": {
    "price": 0.0018,
    "currency": "ETH"
  },
  "alexander-arnold": {
    "price": 0.1052,
    "currency": "ETH"
  },
  "cucurella": {
    "price": 7.95,
    "currency": "EUR"
  },
  "konate": {
    "price": 4.98,
    "currency": "EUR"
  },
  "valverde": {
    "price": 10.9,
    "currency": "EUR"
  },
  "camavinga": {
    "price": 3.45,
    "currency": "EUR"
  },
  "tchouameni": {
    "price": 11.39,
    "currency": "EUR"
  },
  "bellingham": {
    "price": 34.3,
    "currency": "EUR"
  },
  "arda-guler": {
    "price": 17.89,
    "currency": "EUR"
  },
  "bernardo-silva": {
    "price": 0.007,
    "currency": "ETH"
  },
  "vinicius": {
    "price": 22.87,
    "currency": "EUR"
  },
  "rodrygo": {
    "price": 5.99,
    "currency": "EUR"
  },
  "brahim": {
    "price": 3.2,
    "currency": "EUR"
  },
  "mbappe": {
    "price": 99.0,
    "currency": "EUR"
  },
  "gonzalo-garcia": {
    "price": 4.02,
    "currency": "EUR"
  },
  "mastantuono": {
    "price": 0.0049,
    "currency": "ETH"
  },
  "endrick": {
    "price": 12.39,
    "currency": "EUR"
  },
  "joan-garcia": {
    "price": 0.0194,
    "currency": "ETH"
  },
  "szczesny": {
    "price": 3.07,
    "currency": "EUR"
  },
  "ter-stegen": {
    "price": 8.9,
    "currency": "EUR"
  },
  "araujo": {
    "price": 1.34,
    "currency": "EUR"
  },
  "kounde": {
    "price": 6.78,
    "currency": "EUR"
  },
  "balde": {
    "price": 3.0,
    "currency": "EUR"
  },
  "cubarsi": {
    "price": 30.67,
    "currency": "EUR"
  },
  "christensen": {
    "price": 1.18,
    "currency": "EUR"
  },
  "eric-garcia": {
    "price": 4.49,
    "currency": "EUR"
  },
  "gerard-martin": {
    "price": 4.11,
    "currency": "EUR"
  },
  "hector-fort": {
    "price": 1.95,
    "currency": "EUR"
  },
  "de-jong": {
    "price": 5.45,
    "currency": "EUR"
  },
  "pedri": {
    "price": 42.9,
    "currency": "EUR"
  },
  "gavi": {
    "price": 4.4,
    "currency": "EUR"
  },
  "fermin-lopez": {
    "price": 9.74,
    "currency": "EUR"
  },
  "olmo": {
    "price": 5.81,
    "currency": "EUR"
  },
  "casado": {
    "price": 2.66,
    "currency": "EUR"
  },
  "bernal": {
    "price": 6.83,
    "currency": "EUR"
  },
  "ferran-torres": {
    "price": 4.59,
    "currency": "EUR"
  },
  "raphinha": {
    "price": 0.032,
    "currency": "ETH"
  },
  "yamal": {
    "price": 125.0,
    "currency": "EUR"
  },
  "bardghji": {
    "price": 4.95,
    "currency": "EUR"
  },
  "gordon": {
    "price": 0.0186,
    "currency": "ETH"
  },
  "luiz-junior": {
    "price": 0.011,
    "currency": "ETH"
  },
  "diego-conde": {
    "price": 1.97,
    "currency": "EUR"
  },
  "arnau-tenas": {
    "price": 10.99,
    "currency": "EUR"
  },
  "juan-foyth": {
    "price": 0.44,
    "currency": "EUR"
  },
  "sergi-cardona": {
    "price": 0.41,
    "currency": "EUR"
  },
  "pau-navarro": {
    "price": 1.21,
    "currency": "EUR"
  },
  "logan-costa": {
    "price": 0.46,
    "currency": "EUR"
  },
  "renato-veiga": {
    "price": 0.0039,
    "currency": "ETH"
  },
  "alvaro-mourino": {
    "price": 0.47,
    "currency": "EUR"
  },
  "willy-kambwala": {
    "price": 1.19,
    "currency": "EUR"
  },
  "alexander-freeman": {
    "price": 0.001,
    "currency": "ETH"
  },
  "carlos-romero": {
    "price": 2.1,
    "currency": "EUR"
  },
  "santiago-comesana": {
    "price": 1.8,
    "currency": "EUR"
  },
  "pape-gueye": {
    "price": 0.92,
    "currency": "EUR"
  },
  "tajon-buchanan": {
    "price": 0.42,
    "currency": "EUR"
  },
  "thomas-partey": {
    "price": 0.39,
    "currency": "EUR"
  },
  "gerard-moreno": {
    "price": 2.41,
    "currency": "EUR"
  },
  "nicolas-pepe": {
    "price": 0.0012,
    "currency": "ETH"
  },
  "georges-mikautadze": {
    "price": 2.4,
    "currency": "EUR"
  },
  "tani-oluwaseyi": {
    "price": 0.42,
    "currency": "EUR"
  },
  "pau-cabanes": {
    "price": 0.42,
    "currency": "EUR"
  },
  "ilias-akhomach": {
    "price": 0.46,
    "currency": "EUR"
  },
  "thiago-fernandez": {
    "price": 0.59,
    "currency": "EUR"
  },
  "thibaut-courtois": {
    "price": 25.0,
    "currency": "EUR"
  },
  "andriy-lunin": {
    "price": 4.0,
    "currency": "EUR"
  },
  "eder-militao": {
    "price": 4.1,
    "currency": "EUR"
  },
  "antonio-rudiger": {
    "price": 1.0,
    "currency": "EUR"
  },
  "trent-alexander-arnold": {
    "price": 5.0,
    "currency": "EUR"
  },
  "ferland-mendy": {
    "price": 1.0,
    "currency": "EUR"
  },
  "marc-cucurella": {
    "price": 7.95,
    "currency": "EUR"
  },
  "ibrahima-konate": {
    "price": 4.98,
    "currency": "EUR"
  },
  "denzel-dumfries": {
    "price": 0.013,
    "currency": "ETH"
  },
  "jude-bellingham": {
    "price": 34.3,
    "currency": "EUR"
  },
  "federico-valverde": {
    "price": 10.99,
    "currency": "EUR"
  },
  "aurelien-tchouameni": {
    "price": 11.39,
    "currency": "EUR"
  },
  "eduardo-camavinga": {
    "price": 3.45,
    "currency": "EUR"
  },
  "brahim-diaz": {
    "price": 3.2,
    "currency": "EUR"
  },
  "vinicius-junior": {
    "price": 22.87,
    "currency": "EUR"
  },
  "kylian-mbappe": {
    "price": 99.5,
    "currency": "EUR"
  },
  "wojciech-szczesny": {
    "price": 3.07,
    "currency": "EUR"
  },
  "pau-cubarsi": {
    "price": 30.67,
    "currency": "EUR"
  },
  "ronald-araujo": {
    "price": 1.34,
    "currency": "EUR"
  },
  "andreas-christensen": {
    "price": 1.18,
    "currency": "EUR"
  },
  "alejandro-balde": {
    "price": 3.0,
    "currency": "EUR"
  },
  "jules-kounde": {
    "price": 6.8,
    "currency": "EUR"
  },
  "marc-bernal": {
    "price": 6.83,
    "currency": "EUR"
  },
  "marc-casado": {
    "price": 2.66,
    "currency": "EUR"
  },
  "frenkie-de-jong": {
    "price": 5.45,
    "currency": "EUR"
  },
  "dani-olmo": {
    "price": 5.81,
    "currency": "EUR"
  },
  "anthony-gordon": {
    "price": 10.0,
    "currency": "EUR"
  },
  "lamine-yamal": {
    "price": 125.0,
    "currency": "EUR"
  },
  "roony-bardghji": {
    "price": 4.95,
    "currency": "EUR"
  },
  "santi-comesana": {
    "price": 1.8,
    "currency": "EUR"
  },
  "alberto-moleiro": {
    "price": 1.59,
    "currency": "EUR"
  },
  "ayoze-perez": {
    "price": 2.3,
    "currency": "EUR"
  },
  "daniel-parejo": {
    "price": 0.48,
    "currency": "EUR"
  },
  "jan-oblak": {
    "price": 9.95,
    "currency": "EUR"
  },
  "jose-maria-gimenez": {
    "price": 0.47,
    "currency": "EUR"
  },
  "david-hancko": {
    "price": 0.001,
    "currency": "ETH"
  },
  "marc-pubill": {
    "price": 3.2,
    "currency": "EUR"
  },
  "nahuel-molina": {
    "price": 0.8,
    "currency": "EUR"
  },
  "alejandro-grimaldo": {
    "price": 5.26,
    "currency": "EUR"
  },
  "matteo-ruggeri": {
    "price": 0.95,
    "currency": "EUR"
  },
  "koke": {
    "price": 0.55,
    "currency": "EUR"
  },
  "pablo-barrios": {
    "price": 2.12,
    "currency": "EUR"
  },
  "johnny-cardoso": {
    "price": 0.0262,
    "currency": "ETH"
  },
  "thomas-lemar": {
    "price": 0.35,
    "currency": "EUR"
  },
  "alex-baena": {
    "price": 3.27,
    "currency": "EUR"
  },
  "ademola-lookman": {
    "price": 13.0,
    "currency": "EUR"
  },
  "julian-alvarez": {
    "price": 59.9,
    "currency": "EUR"
  },
  "antoine-griezmann": {
    "price": 55.0,
    "currency": "EUR"
  },
  "giuliano-simeone": {
    "price": 0.0011,
    "currency": "ETH"
  },
  "carlos-martin": {
    "price": 0.44,
    "currency": "EUR"
  },
  "alvaro-valles": {
    "price": 4.5,
    "currency": "EUR"
  },
  "pau-lopez": {
    "price": 1.09,
    "currency": "EUR"
  },
  "hector-bellerin": {
    "price": 0.47,
    "currency": "EUR"
  },
  "diego-llorente": {
    "price": 0.44,
    "currency": "EUR"
  },
  "natan": {
    "price": 0.65,
    "currency": "EUR"
  },
  "marc-bartra": {
    "price": 0.38,
    "currency": "EUR"
  },
  "ricardo-rodriguez": {
    "price": 1.22,
    "currency": "EUR"
  },
  "junior-firpo": {
    "price": 0.44,
    "currency": "EUR"
  },
  "sergi-altimira": {
    "price": 1.35,
    "currency": "EUR"
  },
  "pablo-fornals": {
    "price": 1.55,
    "currency": "EUR"
  },
  "alvaro-fidalgo": {
    "price": 1.2,
    "currency": "EUR"
  },
  "giovani-lo-celso": {
    "price": 0.6,
    "currency": "EUR"
  },
  "isco": {
    "price": 3.32,
    "currency": "EUR"
  },
  "antony": {
    "price": 8.2,
    "currency": "EUR"
  },
  "abde-ezzalzouli": {
    "price": 6.54,
    "currency": "EUR"
  },
  "cucho-hernandez": {
    "price": 0.0007,
    "currency": "ETH"
  },
  "aitor-ruibal": {
    "price": 0.32,
    "currency": "EUR"
  },
  "ivan-villar": {
    "price": 0.41,
    "currency": "EUR"
  },
  "javi-galan": {
    "price": 0.46,
    "currency": "EUR"
  },
  "carl-starfelt": {
    "price": 0.32,
    "currency": "EUR"
  },
  "marcos-alonso": {
    "price": 0.32,
    "currency": "EUR"
  },
  "carlos-dominguez": {
    "price": 0.32,
    "currency": "EUR"
  },
  "javi-rodriguez": {
    "price": 0.6,
    "currency": "EUR"
  },
  "aleix-febas": {
    "price": 5.75,
    "currency": "EUR"
  },
  "carlos-dotor": {
    "price": 0.0032,
    "currency": "ETH"
  },
  "ilaix-moriba": {
    "price": 1.05,
    "currency": "EUR"
  },
  "matias-vecino": {
    "price": 0.38,
    "currency": "EUR"
  },
  "williot-swedberg": {
    "price": 0.0006,
    "currency": "ETH"
  },
  "hugo-alvarez": {
    "price": 0.6,
    "currency": "EUR"
  },
  "carles-perez": {
    "price": 0.0003,
    "currency": "ETH"
  },
  "borja-iglesias": {
    "price": 0.4,
    "currency": "EUR"
  },
  "iago-aspas": {
    "price": 0.31,
    "currency": "EUR"
  }
}