{
  "metadata": {
    "first_run": "2026-07-21T09:09:18.763866Z",
    "last_run": "2026-07-21T09:46:05.759099Z",
    "total_runs": 8
  },
  "summary": {
    "global_average_price_eur": 6.32,
    "global_trend": "STABLE",
    "trend_change_pct": 0.0,
    "top10_movers": []
  },
  "teams": {
    "atlanta-united": {
      "team_name": "Atlanta United",
      "players": {
        "mohammed-sofo": {
          "name": "Mohammed Sofo",
          "prices_this_run": [
            1.29
          ],
          "min_live_price": 1.29,
          "max_live_price": 1.29,
          "historical_mean": 1.29,
          "std_dev": 0,
          "occurrences": 1,
          "change_from_mean_pct": 0.0,
          "first_seen": "2026-07-21T09:09:44.625881Z",
          "last_update": "2026-07-21T09:09:44.625901Z"
        },
        "petar-musa": {
          "name": "Petar Musa",
          "prices_this_run": [
            6.9
          ],
          "min_live_price": 6.9,
          "max_live_price": 6.9,
          "historical_mean": 6.9,
          "std_dev": 0,
          "occurrences": 1,
          "change_from_mean_pct": 0.0,
          "first_seen": "2026-07-21T09:12:36.148123Z",
          "last_update": "2026-07-21T09:12:36.148141Z"
        },
        "alisa-randell": {
          "name": "D. Randell",
          "prices_this_run": [
            2.07
          ],
          "min_live_price": 2.07,
          "max_live_price": 2.07,
          "historical_mean": 2.07,
          "std_dev": 0,
          "occurrences": 1,
          "change_from_mean_pct": 0.0,
          "first_seen": "2026-07-21T09:16:07.212595Z",
          "last_update": "2026-07-21T09:16:07.212611Z"
        },
        "n-riman-axundzad": {
          "name": "Nəriman Axundzadə",
          "prices_this_run": [
            0.99
          ],
          "min_live_price": 0.99,
          "max_live_price": 0.99,
          "historical_mean": 0.99,
          "std_dev": 0,
          "occurrences": 1,
          "change_from_mean_pct": 0.0,
          "first_seen": "2026-07-21T09:16:43.122332Z",
          "last_update": "2026-07-21T09:16:43.122346Z"
        },
        "philip-zinckernagel": {
          "name": "Philip Zinckernagel",
          "prices_this_run": [
            42.99,
            43.78
          ],
          "min_live_price": 42.99,
          "max_live_price": 43.78,
          "historical_mean": 43.385000000000005,
          "std_dev": 0.558614357137372,
          "occurrences": 2,
          "change_from_mean_pct": -0.9,
          "first_seen": "2026-07-21T09:16:51.746153Z",
          "last_update": "2026-07-21T09:16:58.553730Z"
        },
        "felipe-andres-mora-aliaga": {
          "name": "Felipe Mora",
          "prices_this_run": [
            1.25
          ],
          "min_live_price": 1.25,
          "max_live_price": 1.25,
          "historical_mean": 1.25,
          "std_dev": 0,
          "occurrences": 1,
          "change_from_mean_pct": 0.0,
          "first_seen": "2026-07-21T09:16:58.957887Z",
          "last_update": "2026-07-21T09:16:58.957901Z"
        },
        "artem-smolyakov": {
          "name": "Artem Smoliakov",
          "prices_this_run": [
            2.98
          ],
          "min_live_price": 2.98,
          "max_live_price": 2.98,
          "historical_mean": 2.98,
          "std_dev": 0,
          "occurrences": 1,
          "change_from_mean_pct": 0.0,
          "first_seen": "2026-07-21T09:17:30.910837Z",
          "last_update": "2026-07-21T09:17:30.910852Z"
        },
        "ashley-westwood": {
          "name": "Ashley Westwood",
          "prices_this_run": [
            3.12
          ],
          "min_live_price": 3.12,
          "max_live_price": 3.12,
          "historical_mean": 3.12,
          "std_dev": 0,
          "occurrences": 1,
          "change_from_mean_pct": 0.0,
          "first_seen": "2026-07-21T09:21:03.702226Z",
          "last_update": "2026-07-21T09:21:03.702243Z"
        },
        "mohamed-farsi": {
          "name": "Mohamed Farsi",
          "prices_this_run": [
            1.5
          ],
          "min_live_price": 1.5,
          "max_live_price": 1.5,
          "historical_mean": 1.5,
          "std_dev": 0,
          "occurrences": 1,
          "change_from_mean_pct": 0.0,
          "first_seen": "2026-07-21T09:21:04.142261Z",
          "last_update": "2026-07-21T09:21:04.142275Z"
        },
        "nathan-byrne": {
          "name": "Nathan Byrne",
          "prices_this_run": [
            2.15
          ],
          "min_live_price": 2.15,
          "max_live_price": 2.15,
          "historical_mean": 2.15,
          "std_dev": 0,
          "occurrences": 1,
          "change_from_mean_pct": 0.0,
          "first_seen": "2026-07-21T09:21:19.420070Z",
          "last_update": "2026-07-21T09:21:19.420084Z"
        },
        "amar-sejdic": {
          "name": "Amar Sejdić",
          "prices_this_run": [
            0.9
          ],
          "min_live_price": 0.9,
          "max_live_price": 0.9,
          "historical_mean": 0.9,
          "std_dev": 0,
          "occurrences": 1,
          "change_from_mean_pct": 0.0,
          "first_seen": "2026-07-21T09:21:24.953785Z",
          "last_update": "2026-07-21T09:21:24.953801Z"
        },
        "joao-gabriel-martins-peglow": {
          "name": "Peglow",
          "prices_this_run": [
            3.03
          ],
          "min_live_price": 3.03,
          "max_live_price": 3.03,
          "historical_mean": 3.03,
          "std_dev": 0,
          "occurrences": 1,
          "change_from_mean_pct": 0.0,
          "first_seen": "2026-07-21T09:21:37.550988Z",
          "last_update": "2026-07-21T09:21:37.551004Z"
        },
        "erik-thommy": {
          "name": "Erik Thommy",
          "prices_this_run": [
            0.9
          ],
          "min_live_price": 0.9,
          "max_live_price": 0.9,
          "historical_mean": 0.9,
          "std_dev": 0,
          "occurrences": 1,
          "change_from_mean_pct": 0.0,
          "first_seen": "2026-07-21T09:21:55.629872Z",
          "last_update": "2026-07-21T09:21:55.629893Z"
        },
        "onni-valakari": {
          "name": "Onni Valakari",
          "prices_this_run": [
            4.74
          ],
          "min_live_price": 4.74,
          "max_live_price": 4.74,
          "historical_mean": 4.74,
          "std_dev": 0,
          "occurrences": 1,
          "change_from_mean_pct": 0.0,
          "first_seen": "2026-07-21T09:21:57.591963Z",
          "last_update": "2026-07-21T09:21:57.591978Z"
        },
        "taha-habroune": {
          "name": "Taha Habroune",
          "prices_this_run": [
            2.96
          ],
          "min_live_price": 2.96,
          "max_live_price": 2.96,
          "historical_mean": 2.96,
          "std_dev": 0,
          "occurrences": 1,
          "change_from_mean_pct": 0.0,
          "first_seen": "2026-07-21T09:22:16.007297Z",
          "last_update": "2026-07-21T09:22:16.007312Z"
        },
        "alhassan-yusuf": {
          "name": "Alhassan Yusuf",
          "prices_this_run": [
            4.64
          ],
          "min_live_price": 4.64,
          "max_live_price": 4.64,
          "historical_mean": 4.64,
          "std_dev": 0,
          "occurrences": 1,
          "change_from_mean_pct": 0.0,
          "first_seen": "2026-07-21T09:22:16.998444Z",
          "last_update": "2026-07-21T09:22:16.998459Z"
        },
        "thomas-guilier": {
          "name": "Thomas Guillier",
          "prices_this_run": [
            6.0
          ],
          "min_live_price": 6.0,
          "max_live_price": 6.0,
          "historical_mean": 6.0,
          "std_dev": 0,
          "occurrences": 1,
          "change_from_mean_pct": 0.0,
          "first_seen": "2026-07-21T09:22:17.924821Z",
          "last_update": "2026-07-21T09:22:17.924836Z"
        },
        "noah-allen": {
          "name": "Noah Allen",
          "prices_this_run": [
            1.3
          ],
          "min_live_price": 1.3,
          "max_live_price": 1.3,
          "historical_mean": 1.3,
          "std_dev": 0,
          "occurrences": 1,
          "change_from_mean_pct": 0.0,
          "first_seen": "2026-07-21T09:22:18.207585Z",
          "last_update": "2026-07-21T09:22:18.207600Z"
        },
        "victor-loturi": {
          "name": "Victor Loturi",
          "prices_this_run": [
            1.2
          ],
          "min_live_price": 1.2,
          "max_live_price": 1.2,
          "historical_mean": 1.2,
          "std_dev": 0,
          "occurrences": 1,
          "change_from_mean_pct": 0.0,
          "first_seen": "2026-07-21T09:22:21.853520Z",
          "last_update": "2026-07-21T09:22:21.853535Z"
        },
        "jordan-morris": {
          "name": "Jordan Morris",
          "prices_this_run": [
            1.5
          ],
          "min_live_price": 1.5,
          "max_live_price": 1.5,
          "historical_mean": 1.5,
          "std_dev": 0,
          "occurrences": 1,
          "change_from_mean_pct": 0.0,
          "first_seen": "2026-07-21T09:22:22.037238Z",
          "last_update": "2026-07-21T09:22:22.037253Z"
        },
        "malik-henry": {
          "name": "Malik Henry",
          "prices_this_run": [
            2.6
          ],
          "min_live_price": 2.6,
          "max_live_price": 2.6,
          "historical_mean": 2.6,
          "std_dev": 0,
          "occurrences": 1,
          "change_from_mean_pct": 0.0,
          "first_seen": "2026-07-21T09:22:46.724047Z",
          "last_update": "2026-07-21T09:22:46.724062Z"
        },
        "julio-joao-ortiz-landazuri": {
          "name": "Julio Ortiz",
          "prices_this_run": [
            0.8
          ],
          "min_live_price": 0.8,
          "max_live_price": 0.8,
          "historical_mean": 0.8,
          "std_dev": 0,
          "occurrences": 1,
          "change_from_mean_pct": 0.0,
          "first_seen": "2026-07-21T09:22:47.538249Z",
          "last_update": "2026-07-21T09:22:47.538265Z"
        },
        "ronald-donkor": {
          "name": "Ronald Donkor",
          "prices_this_run": [
            1.98
          ],
          "min_live_price": 1.98,
          "max_live_price": 1.98,
          "historical_mean": 1.98,
          "std_dev": 0,
          "occurrences": 1,
          "change_from_mean_pct": 0.0,
          "first_seen": "2026-07-21T09:22:52.672456Z",
          "last_update": "2026-07-21T09:22:52.672471Z"
        },
        "logan-farrington": {
          "name": "Logan Farrington",
          "prices_this_run": [
            3.71
          ],
          "min_live_price": 3.71,
          "max_live_price": 3.71,
          "historical_mean": 3.71,
          "std_dev": 0,
          "occurrences": 1,
          "change_from_mean_pct": 0.0,
          "first_seen": "2026-07-21T09:28:42.103873Z",
          "last_update": "2026-07-21T09:28:42.103888Z"
        },
        "micael-dos-santos-silva": {
          "name": "Micael",
          "prices_this_run": [
            4.0
          ],
          "min_live_price": 4.0,
          "max_live_price": 4.0,
          "historical_mean": 4.0,
          "std_dev": 0,
          "occurrences": 1,
          "change_from_mean_pct": 0.0,
          "first_seen": "2026-07-21T09:29:26.378521Z",
          "last_update": "2026-07-21T09:29:26.378535Z"
        },
        "joshua-sargent": {
          "name": "Josh Sargent",
          "prices_this_run": [
            3.52
          ],
          "min_live_price": 3.52,
          "max_live_price": 3.52,
          "historical_mean": 3.52,
          "std_dev": 0,
          "occurrences": 1,
          "change_from_mean_pct": 0.0,
          "first_seen": "2026-07-21T09:40:34.693021Z",
          "last_update": "2026-07-21T09:40:34.693041Z"
        },
        "maxime-crepeau": {
          "name": "Maxime Crépeau",
          "prices_this_run": [
            5.5
          ],
          "min_live_price": 5.5,
          "max_live_price": 5.5,
          "historical_mean": 5.5,
          "std_dev": 0,
          "occurrences": 1,
          "change_from_mean_pct": 0.0,
          "first_seen": "2026-07-21T09:40:58.507684Z",
          "last_update": "2026-07-21T09:40:58.507690Z"
        },
        "pep-biel-mas-jaume": {
          "name": "Pep Biel",
          "prices_this_run": [
            9.99
          ],
          "min_live_price": 9.99,
          "max_live_price": 9.99,
          "historical_mean": 9.99,
          "std_dev": 0,
          "occurrences": 1,
          "change_from_mean_pct": 0.0,
          "first_seen": "2026-07-21T09:41:25.536362Z",
          "last_update": "2026-07-21T09:41:25.536377Z"
        },
        "enea-mihaj": {
          "name": "Enea Mihaj",
          "prices_this_run": [
            1.44
          ],
          "min_live_price": 1.44,
          "max_live_price": 1.44,
          "historical_mean": 1.44,
          "std_dev": 0,
          "occurrences": 1,
          "change_from_mean_pct": 0.0,
          "first_seen": "2026-07-21T09:44:23.059329Z",
          "last_update": "2026-07-21T09:44:23.059344Z"
        },
        "luis-alberto-suarez-diaz": {
          "name": "Luis Suárez",
          "prices_this_run": [
            7.5
          ],
          "min_live_price": 7.5,
          "max_live_price": 7.5,
          "historical_mean": 7.5,
          "std_dev": 0,
          "occurrences": 1,
          "change_from_mean_pct": 0.0,
          "first_seen": "2026-07-21T09:44:37.400472Z",
          "last_update": "2026-07-21T09:44:37.400488Z"
        },
        "noel-caliskan": {
          "name": "Noel Caliskan",
          "prices_this_run": [
            11.024065
          ],
          "min_live_price": 11.024065,
          "max_live_price": 11.024065,
          "historical_mean": 11.024065,
          "std_dev": 0,
          "occurrences": 1,
          "change_from_mean_pct": 0.0,
          "first_seen": "2026-07-21T09:44:37.448413Z",
          "last_update": "2026-07-21T09:44:37.448423Z"
        },
        "hany-mukhtar": {
          "name": "Hany Mukhtar",
          "prices_this_run": [
            19.99
          ],
          "min_live_price": 19.99,
          "max_live_price": 19.99,
          "historical_mean": 19.99,
          "std_dev": 0,
          "occurrences": 1,
          "change_from_mean_pct": 0.0,
          "first_seen": "2026-07-21T09:44:37.752315Z",
          "last_update": "2026-07-21T09:44:37.752332Z"
        },
        "adrian-andres-cubas": {
          "name": "Andrés Cubas",
          "prices_this_run": [
            5.55
          ],
          "min_live_price": 5.55,
          "max_live_price": 5.55,
          "historical_mean": 5.55,
          "std_dev": 0,
          "occurrences": 1,
          "change_from_mean_pct": 0.0,
          "first_seen": "2026-07-21T09:45:12.445671Z",
          "last_update": "2026-07-21T09:45:12.445687Z"
        },
        "niko-tsakiris": {
          "name": "Niko Tsakiris",
          "prices_this_run": [
            7.5
          ],
          "min_live_price": 7.5,
          "max_live_price": 7.5,
          "historical_mean": 7.5,
          "std_dev": 0,
          "occurrences": 1,
          "change_from_mean_pct": 0.0,
          "first_seen": "2026-07-21T09:45:15.641623Z",
          "last_update": "2026-07-21T09:45:15.641639Z"
        }
      }
    },
    "chicago-fire": {
      "team_name": "Chicago Fire",
      "players": {}
    },
    "colorado-rapids": {
      "team_name": "Colorado Rapids",
      "players": {}
    },
    "columbus-crew": {
      "team_name": "Columbus Crew",
      "players": {}
    },
    "dc-united": {
      "team_name": "DC United",
      "players": {}
    },
    "fc-dallas": {
      "team_name": "FC Dallas",
      "players": {}
    },
    "houston-dynamo": {
      "team_name": "Houston Dynamo",
      "players": {}
    },
    "inter-miami": {
      "team_name": "Inter Miami",
      "players": {}
    },
    "la-galaxy": {
      "team_name": "LA Galaxy",
      "players": {}
    },
    "lafc": {
      "team_name": "LAFC",
      "players": {}
    },
    "los-angeles-football-club": {
      "team_name": "LAFC",
      "players": {}
    },
    "minnesota-united": {
      "team_name": "Minnesota United",
      "players": {}
    },
    "montreal-impact": {
      "team_name": "Montreal Impact",
      "players": {}
    },
    "new-england-revolution": {
      "team_name": "New England Revolution",
      "players": {}
    },
    "new-york-city-fc": {
      "team_name": "New York City FC",
      "players": {}
    },
    "new-york-red-bulls": {
      "team_name": "New York Red Bulls",
      "players": {}
    },
    "orlando-city": {
      "team_name": "Orlando City",
      "players": {}
    },
    "philadelphia-union": {
      "team_name": "Philadelphia Union",
      "players": {}
    },
    "portland-timbers": {
      "team_name": "Portland Timbers",
      "players": {}
    },
    "real-salt-lake": {
      "team_name": "Real Salt Lake",
      "players": {}
    },
    "san-diego-loyal": {
      "team_name": "San Diego Loyal",
      "players": {}
    },
    "san-jose-earthquakes": {
      "team_name": "San Jose Earthquakes",
      "players": {}
    },
    "seattle-sounders": {
      "team_name": "Seattle Sounders",
      "players": {}
    },
    "sporting-kansas-city": {
      "team_name": "Sporting Kansas City",
      "players": {}
    },
    "toronto-fc": {
      "team_name": "Toronto FC",
      "players": {}
    },
    "vancouver-whitecaps": {
      "team_name": "Vancouver Whitecaps",
      "players": {}
    },
    "fc-cincinnati": {
      "team_name": "FC Cincinnati",
      "players": {}
    },
    "cf-montreal": {
      "team_name": "CF Montreal",
      "players": {}
    }
  }
}